README.md
argz.py
setup.py
argz.egg-info/PKG-INFO
argz.egg-info/SOURCES.txt
argz.egg-info/dependency_links.txt
argz.egg-info/top_level.txt