Metadata-Version: 2.1
Name: argz
Version: 0.1.4
Summary: Argument parsing for the lazy
Home-page: https://github.com/bnbdr/argz
Author: bnbdr
Author-email: bad.32@outlook.com
License: MIT
Keywords: argument parse args
Platform: UNKNOWN
Classifier: Intended Audience :: Developers
Classifier: Programming Language :: Python :: 2
Classifier: Programming Language :: Python :: 3
Classifier: License :: OSI Approved :: MIT License
Classifier: Operating System :: OS Independent
